uwutilities/__init__.py
uwutilities/uwutilities.py
uwutilities/__pycache__/__init__.cpython-39.pyc
uwutilities/__pycache__/uwutilities.cpython-39.pyc
uwutilities-1.4.4.dist-info/METADATA
uwutilities-1.4.4.dist-info/WHEEL
uwutilities-1.4.4.dist-info/top_level.txt
uwutilities-1.4.4.dist-info/RECORD
