Metadata-Version: 2.1
Name: uwutilities
Version: 1.4.4
Summary: A collection of utilities for python
Home-page: https://github.com/kojhyy/uwutilities
Author: kojhyy
Author-email: l4p0ubelle@gmail.com
License: MIT
Platform: UNKNOWN
Classifier: License :: OSI Approved :: MIT License
Classifier: Programming Language :: Python
Classifier: Programming Language :: Python :: 3
Classifier: Programming Language :: Python :: 3.9
Classifier: Operating System :: OS Independent
Requires-Dist: windows-curses
